[{"_id":"Xbox 360 Controller (XInput STANDARD GAMEPAD)"},
{"_id":"Wireless Controller (STANDARD GAMEPAD Vendor: 054c Product: 09cc)"},
{"_id":"Wireless Controller (STANDARD GAMEPAD Vendor: 054c Product: 05c4)"},
{"_id":"Wireless Controller (STANDARD GAMEPAD Vendor: 054c Product: 0ce6)"},
{"_id":"xinput"},
{"_id":"054c-09cc-Wireless Controller"},
{"_id":"054c-05c4-Wireless Controller"},
{"_id":"Wireless controller (STANDARD GAMEPAD Vendor: 054c Product: 05c4)"},
{"_id":"Generic   USB  Joystick   (Vendor: 0079 Product: 0006)"},
{"_id":"Pro Controller (STANDARD GAMEPAD Vendor: 057e Product: 2009)"},
{"_id":"USB Joystick           (Vendor: 0079 Product: 0006)"},
{"_id":"PS3 GamePad (Vendor: 054c Product: 0268)"},
{"_id":"PLAYSTATION(R)3 Controller (Vendor: 054c Product: 0268)"},
{"_id":"Unknown Gamepad (STANDARD GAMEPAD Vendor: 054c Product: 09cc)"},
{"_id":"Twin USB Joystick (Vendor: 0810 Product: 0001)"},
{"_id":"vJoy - Virtual Joystick (Vendor: 1234 Product: bead)"},
{"_id":"Twin USB Gamepad       (Vendor: 0810 Product: 0001)"},
{"_id":" USB Gamepad           (Vendor: 0810 Product: 0001)"},
{"_id":"DUALSHOCK 4 Wireless Controller Extended Gamepad"},
{"_id":"Wireless Gamepad (STANDARD GAMEPAD Vendor: 057e Product: 2009)"},
{"_id":"Sony Interactive Entertainment Wireless Controller (STANDARD GAMEPAD Vendor: 054c Product: 09cc)"},
{"_id":"Wireless Controller Extended Gamepad"},
{"_id":"054c-0ce6-Wireless Controller"},
{"_id":"Logitech Dual Action (STANDARD GAMEPAD Vendor: 046d Product: c216)"},
{"_id":"Wireless Controller (Vendor: 054c Product: 0ce6)"}]